Metadata-Version: 2.1
Name: hikaru-model-26
Version: 1.1.0
Summary: Hikaru allows you to smoothly move between Kubernetes YAML, Python objects, and Python source, in any direction
Home-page: https://github.com/haxsaw/hikaru
Download-URL: https://github.com/haxsaw/hikaru/archive/1.1.0.tar.gz
Author: Tom Carroll
Author-email: tcarroll@incisivetech.co.uk
License: MIT
Keywords: Kubernetes,modelling,YAML,JSON,modeling,translate,translator,reformatter,transform
Classifier: Development Status :: 5 - Production/Stable
Classifier: Intended Audience :: Developers
Classifier: Intended Audience :: Financial and Insurance Industry
Classifier: Intended Audience :: Information Technology
Classifier: License :: OSI Approved :: MIT License
Classifier: Operating System :: OS Independent
Classifier: Programming Language :: Python :: 3 :: Only
Classifier: Programming Language :: Python :: 3.7
Classifier: Programming Language :: Python :: 3.8
Classifier: Programming Language :: Python :: 3.9
Classifier: Programming Language :: Python :: 3.10
Classifier: Programming Language :: Python :: 3.11
Classifier: Programming Language :: Python :: Implementation
Classifier: Topic :: Software Development
Classifier: Topic :: Software Development :: Code Generators
Classifier: Topic :: Software Development :: Libraries
Classifier: Topic :: Software Development :: Libraries :: Python Modules
Classifier: Topic :: Text Processing :: Markup
Classifier: Topic :: Utilities
Classifier: Typing :: Typed
License-File: LICENSE
Requires-Dist: kubernetes (>=26.1.0)
Requires-Dist: hikaru-core (>=1.1.0)
